yt_community_post_archiver/__init__.py
yt_community_post_archiver/__main__.py
yt_community_post_archiver/archiver.py
yt_community_post_archiver/arguments.py
yt_community_post_archiver/comment.py
yt_community_post_archiver/cookies.py
yt_community_post_archiver/helpers.py
yt_community_post_archiver/post.py
yt_community_post_archiver/post_builder.py
yt_community_post_archiver-0.1.8.dist-info/METADATA
yt_community_post_archiver-0.1.8.dist-info/WHEEL
yt_community_post_archiver-0.1.8.dist-info/entry_points.txt
yt_community_post_archiver-0.1.8.dist-info/licenses/LICENSE
yt_community_post_archiver-0.1.8.dist-info/RECORD
