Metadata-Version: 2.4
Name: yt-community-post-archiver
Version: 0.1.8
Summary: Archives YouTube community posts.
Project-URL: Documentation, https://github.com/Pyreko/yt-community-post-archiver#readme
Project-URL: Issues, https://github.com/Pyreko/yt-community-post-archiver/issues
Project-URL: Source, https://github.com/Pyreko/yt-community-post-archiver
Author-email: Pyreko <25498386+Pyreko@users.noreply.github.com>
License-Expression: Apache-2.0
License-File: LICENSE
Keywords: archiver,cli,community,posts,youtube
Classifier: Development Status :: 4 - Beta
Classifier: Operating System :: OS Independent
Classifier: Programming Language :: Python
Classifier: Programming Language :: Python :: 3.11
Classifier: Programming Language :: Python :: 3.12
Classifier: Programming Language :: Python :: 3.13
Requires-Python: >=3.11
Requires-Dist: attrs==24.2.0
Requires-Dist: beautifulsoup4==4.12.3
Requires-Dist: certifi==2025.8.3
Requires-Dist: charset-normalizer==3.3.2
Requires-Dist: filetype==1.2.0
Requires-Dist: h11==0.16.0
Requires-Dist: idna==3.7
Requires-Dist: outcome==1.3.0.post0
Requires-Dist: pillow==10.4.0
Requires-Dist: pysocks==1.7.1
Requires-Dist: requests==2.32.4
Requires-Dist: selenium==4.35.0
Requires-Dist: sniffio==1.3.0
Requires-Dist: sortedcontainers==2.4.0
Requires-Dist: trio-websocket==0.12.2
Requires-Dist: trio==0.30.0
Requires-Dist: urllib3==2.5.0
Requires-Dist: wsproto==1.2.0
